bitchain/__init__.py
bitchain/__main__.py
bitchain/bitchain.py
bitchain-0.0.0.dist-info/METADATA
bitchain-0.0.0.dist-info/WHEEL
bitchain-0.0.0.dist-info/top_level.txt
bitchain-0.0.0.dist-info/zip-safe
bitchain-0.0.0.dist-info/RECORD
