Metadata-Version: 2.1
Name: bitchain
Version: 0.0.0
Summary: Starling bitchain is a Spatial Python Framework
Home-page: https://www.blockfoundation.io
Download-URL: https://www.blockfoundation.io
Author: Lars van Vianen
Author-email: lars@blockfoundation.io
Maintainer: Starling Associates
Maintainer-email: info@blockfoundation.io
License: MIT
Project-URL: documentation, https://bitchain.pypa.io/
Project-URL: repository, https://github.com/starling-cloud/bitchain
Keywords: starling,bitchain,geometry,geospatial
Classifier: Development Status :: 1 - Planning
Classifier: Intended Audience :: Developers
Classifier: License :: OSI Approved :: MIT License
Classifier: Natural Language :: English
Classifier: Operating System :: OS Independent
Classifier: Programming Language :: Python :: 3 :: Only
Classifier: Topic :: Scientific/Engineering
Classifier: Topic :: Software Development :: Libraries
Requires-Python: >=3.10
